pyprimos_Caleb/__init__.py
pyprimos_Caleb-1.0.dist-info/LICENSE
pyprimos_Caleb-1.0.dist-info/METADATA
pyprimos_Caleb-1.0.dist-info/WHEEL
pyprimos_Caleb-1.0.dist-info/top_level.txt
pyprimos_Caleb-1.0.dist-info/RECORD
